ai_maintainer_git_util/__init__.py
ai_maintainer_git_util/git_util.py
ai_maintainer_git_util-0.1.1.dist-info/AUTHORS.rst
ai_maintainer_git_util-0.1.1.dist-info/LICENSE
ai_maintainer_git_util-0.1.1.dist-info/METADATA
ai_maintainer_git_util-0.1.1.dist-info/WHEEL
ai_maintainer_git_util-0.1.1.dist-info/top_level.txt
ai_maintainer_git_util-0.1.1.dist-info/RECORD
