Metadata-Version: 2.1
Name: ai-maintainer-git-util
Version: 0.1.1
Summary: A git util for working with the AI Maintainer go git repo in google cloud
Home-page: https://github.com/ai-maintainer-inc/ai_maintainer_git_util
Author: Douglas Schonholtz
Author-email: douglas@ai-maintainer.com
License: MIT license
Keywords: ai_maintainer_git_util
Classifier: Development Status :: 2 - Pre-Alpha
Classifier: Intended Audience :: Developers
Classifier: License :: OSI Approved :: MIT License
Classifier: Natural Language :: English
Classifier: Programming Language :: Python :: 3
Classifier: Programming Language :: Python :: 3.8
Classifier: Programming Language :: Python :: 3.9
Classifier: Programming Language :: Python :: 3.10
Requires-Python: >=3.8
License-File: LICENSE
License-File: AUTHORS.rst
